amptk/OTU_cluster.py
amptk/OTU_cluster_ref.py
amptk/__init__.py
amptk/__version__.py
amptk/amptk.py
amptk/amptklib.py
amptk/assign_taxonomy.py
amptk/barcode_rarify.py
amptk/check_version.R
amptk/collapse_taxonomy.py
amptk/csv2heatmap.py
amptk/dada2.py
amptk/dada2_pacbio.py
amptk/dada2_pipeline_nofilt.R
amptk/downloads.json
amptk/downloadsv1.6.0.json
amptk/drop.py
amptk/extract_region.py
amptk/fastq2sra.py
amptk/filter.py
amptk/funguild.py
amptk/get_barcode_counts.py
amptk/heatmap.py
amptk/info.py
amptk/install.py
amptk/keep_samples.py
amptk/lulu.py
amptk/merge_metadata.py
amptk/ont_cluster.py
amptk/parse_adonis.py
amptk/phyloseq_nmds.R
amptk/phyloseq_nmds_indicator.R
amptk/primers.json
amptk/process_illumina2.py
amptk/process_illumina_folder.py
amptk/process_illumina_raw.py
amptk/process_ion.py
amptk/process_ont.py
amptk/process_pacbio.py
amptk/pybam.py
amptk/remove_samples.py
amptk/runLULU.R
amptk/stackedBarGraph.py
amptk/stats.py
amptk/summarize_taxonomy.py
amptk/unoise2.py
amptk/unoise3.py
amptk/DB/amptk_mock1.fa
amptk/DB/amptk_mock2.fa
amptk/DB/amptk_mock3.fa
amptk/DB/amptk_synmock.fa
amptk/DB/ioncode_barcodes.fa
amptk/DB/ionxpress_barcodes.fa
amptk-1.6.0.data/scripts/amptk_synthetic_mock.py
amptk-1.6.0.data/scripts/bold2utax.py
amptk-1.6.0.dist-info/LICENSE.md
amptk-1.6.0.dist-info/METADATA
amptk-1.6.0.dist-info/WHEEL
amptk-1.6.0.dist-info/entry_points.txt
amptk-1.6.0.dist-info/top_level.txt
amptk-1.6.0.dist-info/RECORD
