Metadata-Version: 2.1
Name: amptk
Version: 1.6.0
Summary: AMPtk: amplicon tool kit
Home-page: https://github.com/nextgenusfs/amptk
Author: Jon Palmer
Author-email: nextgenusfs@gmail.com
License: BSD-2
Classifier: Development Status :: 4 - Beta
Classifier: License :: OSI Approved :: BSD License
Classifier: Programming Language :: Python
Classifier: Programming Language :: Python :: 2
Classifier: Programming Language :: Python :: 3
Classifier: Operating System :: Unix
Classifier: Intended Audience :: Science/Research
Classifier: Topic :: Scientific/Engineering :: Bio-Informatics
Requires-Python: >=2.7.0, !=3.0.*, !=3.1.*, !=3.2.*
License-File: LICENSE.md
Requires-Dist: edlib
Requires-Dist: numpy
Requires-Dist: pyfastx >=0.8.0
Requires-Dist: biopython
Requires-Dist: matplotlib
Requires-Dist: seaborn
Requires-Dist: psutil
Requires-Dist: pandas
Requires-Dist: requests
Requires-Dist: natsort
Requires-Dist: biom-format
Requires-Dist: distro
